README.md
setup.py
lw_test.egg-info/PKG-INFO
lw_test.egg-info/SOURCES.txt
lw_test.egg-info/dependency_links.txt
lw_test.egg-info/requires.txt
lw_test.egg-info/top_level.txt
sample/__init__.py
sample/simple.py
tests/test1.py