Metadata-Version: 2.1
Name: lw_test
Version: 1.0.0
Summary: A light weight command line menu that supports Windows
Author: lw
Author-email: 2976638734@qq.com
Keywords: python,menu,lw_test,windows,mac,linux
Classifier: Development Status :: 1 - Planning
Classifier: Intended Audience :: Developers
Classifier: Programming Language :: Python :: 3
Classifier: Operating System :: Unix
Classifier: Operating System :: MacOS :: MacOS X
Classifier: Operating System :: Microsoft :: Windows
Requires-Dist: getch; platform_system == "Unix"
Requires-Dist: getch; platform_system == "MacOS"
